ctdcal/__init__.py
ctdcal/__main__.py
ctdcal/_version.py
ctdcal/cfg.yaml
ctdcal/common.py
ctdcal/config.py
ctdcal/convert.py
ctdcal/ctd_plots.py
ctdcal/equations_sbe.py
ctdcal/fit_ctd.py
ctdcal/flagging.py
ctdcal/io.py
ctdcal/odf_io.py
ctdcal/oxy_fitting.py
ctdcal/process_bottle.py
ctdcal/process_ctd.py
ctdcal/rinko.py
ctdcal/sbe_reader.py
ctdcal/settings.py
ctdcal/user_settings.yaml
ctdcal/fitting/__init__.py
ctdcal/fitting/common.py
ctdcal/fitting/tests/__init__.py
ctdcal/fitting/tests/test_common.py
ctdcal/processors/__init__.py
ctdcal/processors/cast_tools.py
ctdcal/processors/tests/__init__.py
ctdcal/processors/tests/test_cast_tools.py
ctdcal/scripts/__init__.py
ctdcal/scripts/cruise_report.py
ctdcal/scripts/ctd_to_bottle.py
ctdcal/scripts/odf_codes_plots.py
ctdcal/scripts/odf_convert_sbe.py
ctdcal/scripts/odf_process_all.py
ctdcal/scripts/odf_process_bottle.py
ctdcal/scripts/quick_convert.py
ctdcal/tests/__init__.py
ctdcal/tests/test_common.py
ctdcal/tests/test_ctd_plots.py
ctdcal/tests/test_equations_sbe.py
ctdcal/tests/test_fit_ctd.py
ctdcal/tests/test_flagging.py
ctdcal/tests/test_io.py
ctdcal/tests/test_main.py
ctdcal/tests/test_odf_io.py
ctdcal/tests/test_oxy_fitting.py
ctdcal/tests/test_process_bottle.py
ctdcal/tests/test_rinko.py
ctdcal/tools/__init__.py
ctdcal/tools/data_qc.py
ctdcal/tools/header_lookup.py
ctdcal-0.1.5b1.dev0.dist-info/LICENSE.md
ctdcal-0.1.5b1.dev0.dist-info/METADATA
ctdcal-0.1.5b1.dev0.dist-info/WHEEL
ctdcal-0.1.5b1.dev0.dist-info/entry_points.txt
ctdcal-0.1.5b1.dev0.dist-info/top_level.txt
ctdcal-0.1.5b1.dev0.dist-info/RECORD
