Metadata-Version: 2.1
Name: ctdcal
Version: 0.1.5b1.dev0
Summary: CTD and bottle data processing package from UCSD ODF
Home-page: https://github.com/SIO-ODF/ctdcal
Author: "Joseph Gum, Andrew Barna, Michael Kovatch, Aaron Mau, Allen Smith"
Author-email: ajmau@ucsd.edu
Keywords: oceanography,seawater,TEOS-10,ctd,calibration
Platform: any
Classifier: Development Status :: 4 - Beta
Classifier: Environment :: Console
Classifier: Intended Audience :: Science/Research
Classifier: License :: OSI Approved :: BSD License
Classifier: Operating System :: OS Independent
Classifier: Programming Language :: Python
Classifier: Programming Language :: Python :: 3 :: Only
Classifier: Programming Language :: Python :: 3.10
Classifier: Programming Language :: Python :: 3.11
Classifier: Topic :: Scientific/Engineering
Requires-Python: >=3.8
License-File: LICENSE.md
Requires-Dist: click==8.0.1
Requires-Dist: gsw
Requires-Dist: matplotlib
Requires-Dist: munch
Requires-Dist: numpy<2.0.0
Requires-Dist: pandas
Requires-Dist: PyYAML
Requires-Dist: requests
Requires-Dist: scipy
Provides-Extra: complete
Requires-Dist: black; extra == "complete"
Requires-Dist: flake8; extra == "complete"
Requires-Dist: isort; extra == "complete"
Requires-Dist: pre-commit; extra == "complete"
Requires-Dist: pytest; extra == "complete"
Requires-Dist: bokeh; extra == "complete"
Requires-Dist: mypy; extra == "complete"
Requires-Dist: pytest-cov; extra == "complete"
Requires-Dist: Sphinx==7.3.3; extra == "complete"
Requires-Dist: jupyter==1.0.0; extra == "complete"
Requires-Dist: furo==2024.1.29; extra == "complete"
Requires-Dist: nbsphinx==0.9.4; extra == "complete"
Requires-Dist: jupytext; extra == "complete"
Provides-Extra: dev
Requires-Dist: black; extra == "dev"
Requires-Dist: flake8; extra == "dev"
Requires-Dist: isort; extra == "dev"
Requires-Dist: pre-commit; extra == "dev"
Requires-Dist: pytest; extra == "dev"
Provides-Extra: docs
Requires-Dist: Sphinx==7.3.3; extra == "docs"
Requires-Dist: jupyter==1.0.0; extra == "docs"
Requires-Dist: furo==2024.1.29; extra == "docs"
Requires-Dist: nbsphinx==0.9.4; extra == "docs"
Requires-Dist: jupytext; extra == "docs"
Provides-Extra: tests
Requires-Dist: black; extra == "tests"
Requires-Dist: flake8; extra == "tests"
Requires-Dist: isort; extra == "tests"
Requires-Dist: pre-commit; extra == "tests"
Requires-Dist: pytest; extra == "tests"
Requires-Dist: bokeh; extra == "tests"
Requires-Dist: mypy; extra == "tests"
Requires-Dist: pytest-cov; extra == "tests"
